rfGengou.py
rfGengouCmd.py
rfgengou
rfgengou.bat
setup.py
rfGengou.egg-info/PKG-INFO
rfGengou.egg-info/SOURCES.txt
rfGengou.egg-info/dependency_links.txt
rfGengou.egg-info/top_level.txt