Metadata-Version: 1.1
Name: rfGengou
Version: 0.4
Summary: Translate A.D. to Regnal year, and other in Japanese.
Home-page: https://github.com/hATrayflood/rfGengou
Author: hATrayflood
Author-email: h.rayflood@gmail.com
License: The MIT License (MIT)
Platform: UNKNOWN
Classifier: Development Status :: 4 - Beta
Classifier: Environment :: Console
Classifier: Intended Audience :: Developers
Classifier: License :: OSI Approved :: MIT License
Classifier: Natural Language :: Japanese
Classifier: Programming Language :: Python
Classifier: Programming Language :: Python :: 2
Classifier: Programming Language :: Python :: 3
Classifier: Topic :: Office/Business
Classifier: Topic :: Sociology :: Genealogy
Classifier: Topic :: Sociology :: History
Classifier: Topic :: Software Development :: Libraries :: Python Modules
Classifier: Topic :: Text Processing :: Filters
